spotlight/__init__.py
spotlight/cross_validation.py
spotlight/evaluation.py
spotlight/helpers.py
spotlight/interactions.py
spotlight/layers.py
spotlight/losses.py
spotlight/sampling.py
spotlight/torch_utils.py
spotlight/datasets/__init__.py
spotlight/datasets/_transport.py
spotlight/datasets/amazon.py
spotlight/datasets/goodbooks.py
spotlight/datasets/movielens.py
spotlight/datasets/synthetic.py
spotlight/factorization/__init__.py
spotlight/factorization/_components.py
spotlight/factorization/explicit.py
spotlight/factorization/implicit.py
spotlight/factorization/representations.py
spotlight/sequence/__init__.py
spotlight/sequence/implicit.py
spotlight/sequence/representations.py
marslight-0.1.6.dist-info/AUTHORS
marslight-0.1.6.dist-info/LICENSE
marslight-0.1.6.dist-info/METADATA
marslight-0.1.6.dist-info/WHEEL
marslight-0.1.6.dist-info/top_level.txt
marslight-0.1.6.dist-info/RECORD
