Metadata-Version: 2.1
Name: marslight
Version: 0.1.6
Summary: UNKNOWN
Home-page: UNKNOWN
License: MIT
Platform: UNKNOWN
Classifier: Development Status :: 3 - Alpha
Classifier: License :: OSI Approved :: MIT License
Classifier: Topic :: Scientific/Engineering :: Artificial Intelligence
License-File: LICENSE
License-File: AUTHORS
Requires-Dist: torch (>=0.4.0)
